tonie_sync/__init__.py
tonie_sync/__main__.py
tonie_sync/py.typed
tonie_sync/sync_service.py
tonie_sync/utils.py
tonie_sync/clients/__init__.py
tonie_sync/clients/spotdl_client.py
tonie_sync/clients/spotify_client.py
tonie_sync/clients/tonie_client.py
tonie_sync/clients/youtube_client.py
tonie_sync/models/__init__.py
tonie_sync/models/track_metadata.py
tonie_sync-0.1.20.dist-info/METADATA
tonie_sync-0.1.20.dist-info/WHEEL
tonie_sync-0.1.20.dist-info/top_level.txt
tonie_sync-0.1.20.dist-info/RECORD
