Metadata-Version: 2.4
Name: tonie_sync
Version: 0.1.20
Summary: A package to sync Spotify playlists to creative tonies.
Author-email: Anonymous <anonymous@xyz.com>
License: MIT
Project-URL: homepage, https://github.com/sHooPmyWooP/tonie-sync
Requires-Python: <3.14,>=3.10
Requires-Dist: ffmpy<1.0.0,>=0.4.0
Requires-Dist: music-tag<1.0.0,>=0.4.3
Requires-Dist: pillow<11.0.0,>=10.4.0
Requires-Dist: protobuf==3.*
Requires-Dist: tqdm<5.0.0,>=4.66.4
Requires-Dist: tonie-api<1.0.0,>=0.1.1
Requires-Dist: click<9.0.0,>=8.1.7
Requires-Dist: spotdl<5.0.0,>=4.2.10
Requires-Dist: ipykernel>=6.29.5
Requires-Dist: pytubefix>=10.3.6
